yamlium/__init__.py
yamlium/exceptions.py
yamlium/lexer.py
yamlium/nodes.py
yamlium/parser.py
yamlium-0.1.17.dist-info/METADATA
yamlium-0.1.17.dist-info/WHEEL
yamlium-0.1.17.dist-info/licenses/LICENSE
yamlium-0.1.17.dist-info/RECORD
