Metadata-Version: 2.4
Name: yamlium
Version: 0.1.17
Summary: Fast, modern yaml parser and manipulator
Project-URL: Homepage, https://github.com/erikmunkby/yamlium
Project-URL: Documentation, https://github.com/erikmunkby/yamlium
Project-URL: Repository, https://github.com/erikmunkby/yamlium
Project-URL: Issues, https://github.com/erikmunkby/yamlium/issues
Author-email: Erik Munkby <erik.munkby@gmail.com>
License: MIT License
License-File: LICENSE
Classifier: Development Status :: 5 - Production/Stable
Classifier: Intended Audience :: Developers
Classifier: Intended Audience :: Science/Research
Classifier: License :: OSI Approved :: MIT License
Classifier: Operating System :: OS Independent
Classifier: Programming Language :: Python :: 3 :: Only
Requires-Python: >=3.10
